main.py
einas_1.egg-info/PKG-INFO
einas_1.egg-info/SOURCES.txt
einas_1.egg-info/dependency_links.txt
einas_1.egg-info/top_level.txt