Metadata-Version: 2.1
Name: einas-1
Version: 1
Summary: This is a sample package generated with a common summary.
Home-page: UNKNOWN
License: UNKNOWN
Platform: UNKNOWN
